cbsodata/__init__.py
cbsodata/__main__.py
cbsodata/_version.py
cbsodata/cbsodata3.py
cbsodata-1.3.5.dist-info/LICENSE.txt
cbsodata-1.3.5.dist-info/METADATA
cbsodata-1.3.5.dist-info/WHEEL
cbsodata-1.3.5.dist-info/entry_points.txt
cbsodata-1.3.5.dist-info/top_level.txt
cbsodata-1.3.5.dist-info/RECORD
